server/__init__.py
server/msgr_server.py
server/common/__init__.py
server/common/utils.py
server/common/variables.py
server/log/__init__.py
server/log/client_log_config.py
server/log/server_log_config.py
server/server/__init__.py
server/server/add_user.py
server/server/config_window.py
server/server/core.py
server/server/main_window.py
server/server/remove_user.py
server/server/server_db.py
server/server/stat_window.py
server/tests/__init__.py
server/tests/test_client.py
server/tests/test_server.py
server/tests/test_utils.py
py_mess_gb_04_22_server-0.3.1.dist-info/METADATA
py_mess_gb_04_22_server-0.3.1.dist-info/WHEEL
py_mess_gb_04_22_server-0.3.1.dist-info/top_level.txt
py_mess_gb_04_22_server-0.3.1.dist-info/RECORD
