Metadata-Version: 2.1
Name: py-mess-gb-04-22-server
Version: 0.3.1
Summary: one_machine_messenger_server
Home-page: UNKNOWN
Author: Anton Petrov
Author-email: nesamurai@yandex.ru
License: UNKNOWN
Platform: UNKNOWN
Requires-Dist: PyQt5
Requires-Dist: pycryptodome
Requires-Dist: pycryptodomex
Requires-Dist: sqlalchemy
